queryhound/__init__.py
queryhound/cli.py
queryhound-0.8.1.dist-info/METADATA
queryhound-0.8.1.dist-info/WHEEL
queryhound-0.8.1.dist-info/entry_points.txt
queryhound-0.8.1.dist-info/top_level.txt
queryhound-0.8.1.dist-info/RECORD
